streamlit_ydata_profiling/__init__.py
streamlit_ydata_profiling/__version__.py
streamlit_ydata_profiling/frontend/.prettierrc
streamlit_ydata_profiling/frontend/build/asset-manifest.json
streamlit_ydata_profiling/frontend/build/index.html
streamlit_ydata_profiling/frontend/build/static/js/main.651d5484.js
streamlit_ydata_profiling/frontend/build/static/js/main.651d5484.js.LICENSE.txt
streamlit_ydata_profiling/frontend/build/static/js/main.651d5484.js.map
streamlit_ydata_profiling/frontend/package.json
streamlit_ydata_profiling/frontend/public/index.html
streamlit_ydata_profiling/frontend/src/ProfileReport.tsx
streamlit_ydata_profiling/frontend/src/index.tsx
streamlit_ydata_profiling/frontend/src/react-app-env.d.ts
streamlit_ydata_profiling/frontend/tsconfig.json
streamlit_ydata_profiling/frontend/yarn.lock
streamlit_ydata_profiling-0.2.1a4.dist-info/LICENSE
streamlit_ydata_profiling-0.2.1a4.dist-info/METADATA
streamlit_ydata_profiling-0.2.1a4.dist-info/WHEEL
streamlit_ydata_profiling-0.2.1a4.dist-info/RECORD
