Metadata-Version: 2.1
Name: streamlit-ydata-profiling
Version: 0.2.1a4
Summary: YData Profiling component for Streamlit.
Home-page: https://github.com/pejmans21/streamlit-ydata-profiling
License: MIT
Author: okld
Maintainer: pejmans21
Maintainer-email: pezhmansamadi21@gmail.com
Requires-Python: >=3.10,<3.12
Classifier: Development Status :: 4 - Beta
Classifier: License :: OSI Approved :: MIT License
Classifier: Programming Language :: Python :: 3
Classifier: Programming Language :: Python :: 3.10
Classifier: Programming Language :: Python :: 3.11
Classifier: Programming Language :: Python :: 3 :: Only
Requires-Dist: streamlit (>=1.28.0,<2.0.0)
Requires-Dist: watchdog (>=3.0.0,<4.0.0)
Requires-Dist: ydata-profiling (>=4.6.0,<5.0.0)
Project-URL: Repository, https://github.com/pejmans21/streamlit-ydata-profiling
